Workbook

Sheet Costos
B2: NOXA LIVING — Análisis de Costos y Márgenes
B3: Dispensador Automático de Jabón · Mercado Colombia · Canal MercadoLibre
B5: Texto azul = celda editable (cambia el valor) Texto negro = fórmula automática
B7: COSTOS DIRECTOS POR UNIDAD
B8: Costo del producto (proveedor) | C8: 30000 | D8: Midpoint $20K–$40K. Editar con cotización real.
B9: Empaque (sticker + insert card) | C9: 4000 | D9: Estimado para pedido mínimo 100 unidades.
B10: Envío última milla — promedio nacional | C10: 10000 | D10: Varía: Bogotá $8K, provincias $12K–$15K.
B11: SUBTOTAL — Costos directos | C11: =C8+C9+C10
B13: COSTOS DE CANAL ONLINE (porcentaje sobre precio de venta)
B14: Comisión MercadoLibre — listing Premium | C14: 0.165 | D14: ML Colombia 2024. Clasico = 10.5 %, Premium = 16.5 %.
B15: Procesamiento de pago (Mercado Pago) | C15: 0.0518 | D15: Incluye impuesto al consumo. Verificar con ML.
B16: Devoluciones y ajustes estimados | C16: 0.02 | D16: Estimado conservador ~2 % de transacciones.
B17: TOTAL COMISIONES (%) | C17: =C14+C15+C16
B19: PRECIO DE VENTA (editar para simular escenarios)
B20: Precio B2C — MercadoLibre (público general) | C20: 139900 | D20: ★ Cambia este valor para ver el impacto en márgenes
B21: Precio B2B — Venta directa a empresas / hoteles | C21: 119900 | D21: ★ Sin comisión ML. Válido para pedidos mínimo 3 u.
B23: ANÁLISIS DE MÁRGENES
B24: Comisiones absolutas B2C (en COP) | C24: =C20*C17
B25: Costo total por unidad B2C | C25: =C11+C24
B26: Ganancia neta por unidad B2C | C26: =C20-C25
B27: Margen neto B2C (%) | C27: =IFERROR(C26/C20,0)
B29: Costo total por unidad B2B (sin comisión ML) | C29: =C11 | D29: Mismo costo directo, sin pagar ML.
B30: Ganancia neta por unidad B2B | C30: =C21-C29
B31: Margen neto B2B (%) | C31: =IFERROR(C30/C21,0)
B33: INVERSIÓN INICIAL (costos fijos — se pagan una sola vez)
B34: Logo + guía de identidad visual | C34: 150000
B35: Fotografía profesional de producto | C35: 350000
B36: Empaque inicial (100 stickers + inserts) | C36: 100000
B37: Marketing de lanzamiento (ML Ads + Meta) | C37: 500000
B38: Registro mercantil + trámites | C38: 100000
B39: TOTAL INVERSIÓN INICIAL | C39: =SUM(C34:C38)
B41: PUNTO DE EQUILIBRIO (unidades para recuperar la inversión inicial)
B42: Unidades necesarias — canal B2C (MercadoLibre) | C42: =IFERROR(CEILING(C39/C26,1),"N/A") | D42: unidades vendidas por canal online
B43: Unidades necesarias — canal B2B (venta directa) | C43: =IFERROR(CEILING(C39/C30,1),"N/A") | D43: unidades vendidas directo a empresas

Sheet Escenarios
B2: ESCENARIOS DE PRECIO — Canal B2C (MercadoLibre)
B3: Costos importados de hoja "Costos". Cambia el precio en columna C para simular.
B5: Escenario | C5: Precio de venta | D5: Comisiones ML+pago | E5: Costo total / unidad | F5: Ganancia neta / unidad | G5: Margen neto % | H5: Break-even (unidades)
B6: Economico | C6: 99900 | D6: =C6*Costos!$C$17 | E6: =Costos!$C$11+D6 | F6: =C6-E6 | G6: =IFERROR(F6/C6,0) | H6: =IFERROR(CEILING(Costos!$C$39/F6,1),"N/A")
B7: Entrada premium | C7: 119900 | D7: =C7*Costos!$C$17 | E7: =Costos!$C$11+D7 | F7: =C7-E7 | G7: =IFERROR(F7/C7,0) | H7: =IFERROR(CEILING(Costos!$C$39/F7,1),"N/A")
B8: Premium ★ | C8: 139900 | D8: =C8*Costos!$C$17 | E8: =Costos!$C$11+D8 | F8: =C8-E8 | G8: =IFERROR(F8/C8,0) | H8: =IFERROR(CEILING(Costos!$C$39/F8,1),"N/A")
B9: Lujo | C9: 159900 | D9: =C9*Costos!$C$17 | E9: =Costos!$C$11+D9 | F9: =C9-E9 | G9: =IFERROR(F9/C9,0) | H9: =IFERROR(CEILING(Costos!$C$39/F9,1),"N/A")
B11: ★ Precio recomendado: $139,900 COP. Con primer lote de 25 unidades y marketing de $500K, el break-even se alcanza vendiendo ~16 unidades.

Sheet Proyeccion
B2: PROYECCIÓN MENSUAL — Canal B2C (primeros 3 meses)
B3: Usa el precio B2C y costos de la hoja "Costos". Edita las unidades/mes en fila 6.
C5: Conservador | D5: Moderado | E5: Optimista
B6: Unidades vendidas / mes (★ editar) | C6: 8 | D6: 15 | E6: 25
B7: Precio de venta usado | C7: =Costos!$C$20 | D7: =Costos!$C$20 | E7: =Costos!$C$20
B9: Ingresos brutos | C9: =C6*Costos!$C$20 | D9: =D6*Costos!$C$20 | E9: =E6*Costos!$C$20
B10: Costo mercancía vendida (COGS) | C10: =C6*Costos!$C$11 | D10: =D6*Costos!$C$11 | E10: =E6*Costos!$C$11
B11: Comisiones MercadoLibre + pago | C11: =C9*Costos!$C$17 | D11: =D9*Costos!$C$17 | E11: =E9*Costos!$C$17
B12: GANANCIA BRUTA MENSUAL | C12: =C9-C10-C11 | D12: =D9-D10-D11 | E12: =E9-E10-E11
B13: Margen bruto (%) | C13: =IFERROR(C12/C9,0) | D13: =IFERROR(D12/D9,0) | E13: =IFERROR(E12/E9,0)
B15: Inversión inicial amortizada / mes (÷3) | C15: =Costos!$C$39/3 | D15: =Costos!$C$39/3 | E15: =Costos!$C$39/3
B16: RESULTADO NETO MENSUAL | C16: =C12-C15 | D16: =D12-D15 | E16: =E12-E15
B17: Resultado acumulado (3 meses) | C17: =C16*3 | D17: =D16*3 | E17: =E16*3
B19: Nota: inversión inicial amortizada en 3 meses. A partir del mes 4, el resultado neto = ganancia bruta mensual íntegra.
